dreamav/__init__.py
dreamav/__init__.pyc
dreamav/__main__.py
dreamav/dream.ini
dreamav/backends/__init__.py
dreamav/backends/backend.py
dreamav/backends/wsgi.py
dreamav/cli/__init__.py
dreamav/cli/cli.py
dreamav/core/__init__.py
dreamav/core/predict.py
dreamav/parser/__init__.py
dreamav/parser/pdf_parser.py
dreamav/util/__init__.py
dreamav/util/generate_feature_vector_pdf.py
dreamav/util/preprocess.py
dreamav/util/utils.py
dreamav-0.2.7.dist-info/METADATA
dreamav-0.2.7.dist-info/WHEEL
dreamav-0.2.7.dist-info/entry_points.txt
dreamav-0.2.7.dist-info/top_level.txt
dreamav-0.2.7.dist-info/RECORD
