Metadata-Version: 2.1
Name: dreamav
Version: 0.2.7
Summary: This package is for detecting malicious document
Home-page: https://github.com/kookmin-sw/2019-cap1-2019_8
Author: ['Damin Moon', 'Kihwan Kim', 'HyunSeok Kim', 'Hyeri Jung', 'Yuhan Bang']
Author-email: vmfn0401@gmail.com
License: MIT
Platform: UNKNOWN
